asphalt/templating/__init__.py
asphalt/templating/api.py
asphalt/templating/component.py
asphalt/templating/py.typed
asphalt/templating/utils.py
asphalt/templating/renderers/__init__.py
asphalt/templating/renderers/django.py
asphalt/templating/renderers/jinja2.py
asphalt/templating/renderers/mako.py
asphalt/templating/renderers/tornado.py
asphalt_templating-4.0.0.dist-info/LICENSE
asphalt_templating-4.0.0.dist-info/METADATA
asphalt_templating-4.0.0.dist-info/WHEEL
asphalt_templating-4.0.0.dist-info/entry_points.txt
asphalt_templating-4.0.0.dist-info/top_level.txt
asphalt_templating-4.0.0.dist-info/RECORD
