Metadata-Version: 2.1
Name: asphalt-templating
Version: 4.0.0
Summary: Templating component for the Asphalt framework
Author-email: Alex Grönholm <alex.gronholm@nextday.fi>
License: Apache License 2.0
Project-URL: Homepage, https://github.com/asphalt-framework/asphalt-templating
Classifier: Development Status :: 5 - Production/Stable
Classifier: Intended Audience :: Developers
Classifier: License :: OSI Approved :: Apache Software License
Classifier: Topic :: Text Processing :: General
Classifier: Programming Language :: Python
Classifier: Programming Language :: Python :: 3
Classifier: Programming Language :: Python :: 3.7
Classifier: Programming Language :: Python :: 3.8
Classifier: Programming Language :: Python :: 3.9
Classifier: Programming Language :: Python :: 3.10
Classifier: Programming Language :: Python :: 3.11
Requires-Python: >=3.7
License-File: LICENSE
Requires-Dist: asphalt (~=4.8)
Provides-Extra: django
Requires-Dist: Django (>=1.9.0) ; extra == 'django'
Provides-Extra: doc
Requires-Dist: asphalt-templating[django,jinja2,mako,tornado] ; extra == 'doc'
Requires-Dist: Sphinx (>=1.5) ; extra == 'doc'
Requires-Dist: sphinx-rtd-theme ; extra == 'doc'
Requires-Dist: sphinx-autodoc-typehints (>=1.0.5) ; extra == 'doc'
Requires-Dist: sphinxcontrib-asyncio (>=0.2.0) ; extra == 'doc'
Provides-Extra: jinja2
Requires-Dist: Jinja2 (>=2.7.3) ; extra == 'jinja2'
Provides-Extra: mako
Requires-Dist: Mako (>=1.0.1) ; extra == 'mako'
Provides-Extra: test
Requires-Dist: asphalt-templating[django,jinja2,mako,tornado] ; extra == 'test'
Requires-Dist: pytest ; extra == 'test'
Requires-Dist: pytest-cov ; extra == 'test'
Requires-Dist: pytest-asyncio ; extra == 'test'
Provides-Extra: tornado
Requires-Dist: tornado (>=4.3.0) ; extra == 'tornado'
